Metadata-Version: 1.1
Name: imaginator
Version: 0.1.1.19
Summary: Bringing kids' artwork to life using Stable Diffusion
Home-page: https://github.com/brookehamilton/imaginator
Author: Brooke Hamilton
Author-email: brookehamilton@gmail.com
License: BSD 2-clause
Platform: UNKNOWN
Classifier: Development Status :: 1 - Planning
Classifier: Intended Audience :: End Users/Desktop
Classifier: License :: OSI Approved :: BSD License
Classifier: Operating System :: POSIX :: Linux
Classifier: Programming Language :: Python :: 3
